odoo/addons/stock_quant_history_queued/README.rst
odoo/addons/stock_quant_history_queued/__init__.py
odoo/addons/stock_quant_history_queued/__manifest__.py
odoo/addons/stock_quant_history_queued/i18n/fr.po
odoo/addons/stock_quant_history_queued/i18n/it.po
odoo/addons/stock_quant_history_queued/i18n/nl.po
odoo/addons/stock_quant_history_queued/i18n/stock_quant_history_queued.pot
odoo/addons/stock_quant_history_queued/models/__init__.py
odoo/addons/stock_quant_history_queued/models/stock_quant_history_snapshot.py
odoo/addons/stock_quant_history_queued/readme/CONSTRIBUTORS.rst
odoo/addons/stock_quant_history_queued/readme/DESCRIPTION.md
odoo/addons/stock_quant_history_queued/static/description/icon.png
odoo/addons/stock_quant_history_queued/static/description/index.html
odoo/addons/stock_quant_history_queued/tests/__init__.py
odoo/addons/stock_quant_history_queued/tests/test_stock_quant_history_queued.py
odoo_addon_stock_quant_history_queued-17.0.1.0.0.5.dist-info/METADATA
odoo_addon_stock_quant_history_queued-17.0.1.0.0.5.dist-info/WHEEL
odoo_addon_stock_quant_history_queued-17.0.1.0.0.5.dist-info/top_level.txt
odoo_addon_stock_quant_history_queued-17.0.1.0.0.5.dist-info/RECORD
