Metadata-Version: 2.1
Name: odoo-addon-stock_quant_history_queued
Version: 17.0.1.0.0.5
Requires-Python: >=3.10
Requires-Dist: odoo-addon-queue_job>=17.0dev,<17.1dev
Requires-Dist: odoo-addon-stock_quant_history>=17.0dev,<17.1dev
Requires-Dist: odoo>=17.0a,<17.1dev
Summary: Use Queue jop to generate stock quants snapshots
Home-page: https://github.com/OCA/stock-logistics-reporting
License: AGPL-3
Author: Pierre Verkest <pierreverkest84@gmail.com>, Odoo Community Association (OCA)
Author-email: support@odoo-community.org
Classifier: Programming Language :: Python
Classifier: Framework :: Odoo
Classifier: Framework :: Odoo :: 17.0
Classifier: License :: OSI Approved :: GNU Affero General Public License v3
